indentation/__init__.py
indentation-1.0.2.dist-info/metadata.json
indentation-1.0.2.dist-info/DESCRIPTION.rst
indentation-1.0.2.dist-info/RECORD
indentation-1.0.2.dist-info/WHEEL
indentation-1.0.2.dist-info/METADATA
indentation-1.0.2.dist-info/top_level.txt
