Metadata-Version: 2.0
Name: indentation
Version: 1.0.2
Summary: Text indentation functions.
Home-page: https://github.com/hweickert/indentation
Author: Henry Weickert
Author-email: henryweickert@gmail.com
License: UNKNOWN
Keywords: indentation,indent,text
Platform: UNKNOWN
